json2graph/__init__.py
json2graph/decode.py
json2graph/decoder/__init__.py
json2graph/decoder/decode_general.py
json2graph/decoder/decode_main.py
json2graph/decoder/decode_obj_class.py
json2graph/decoder/decode_obj_diagram.py
json2graph/decoder/decode_obj_elementview.py
json2graph/decoder/decode_obj_generalization.py
json2graph/decoder/decode_obj_generalizationset.py
json2graph/decoder/decode_obj_package.py
json2graph/decoder/decode_obj_path.py
json2graph/decoder/decode_obj_project.py
json2graph/decoder/decode_obj_property.py
json2graph/decoder/decode_obj_rectangularshape.py
json2graph/decoder/decode_obj_relation.py
json2graph/library.py
json2graph/modules/__init__.py
json2graph/modules/arguments.py
json2graph/modules/errors.py
json2graph/modules/input_output.py
json2graph/modules/logger.py
json2graph/modules/messages.py
json2graph/modules/metadata.py
json2graph/modules/sparql_queries.py
json2graph/modules/utils_general.py
json2graph/modules/utils_graph.py
json2graph/modules/utils_validations.py
json2graph/resources/logo-json2graph-reduced.png
json2graph/resources/logo-json2graph.png
json2graph/resources/metadata.yaml
json2graph/resources/ontouml_v1.0.0.ttl
json2graph/resources/ontouml_v1.1.0.ttl
ontouml_json2graph-1.3.2.dist-info/LICENSE
ontouml_json2graph-1.3.2.dist-info/METADATA
ontouml_json2graph-1.3.2.dist-info/WHEEL
ontouml_json2graph-1.3.2.dist-info/RECORD
