Metadata-Version: 2.1
Name: ontouml-json2graph
Version: 1.3.2
Summary: OntoUML JSON2Graph Decoder
Home-page: https://w3id.org/ontouml/json2graph
License: Apache-2.0
Keywords: semantic-web,knowledge-graph,ontouml,ontology-driven-development,ontouml-schema,ontouml-vocabulary,ontouml-metamodel
Author: Pedro Paulo F. Barcelos
Author-email: p.p.favatobarcelos@utwente.nl
Requires-Python: >=3.9,<4.0
Classifier: License :: OSI Approved :: Apache Software License
Classifier: Programming Language :: Python :: 3
Classifier: Programming Language :: Python :: 3.9
Classifier: Programming Language :: Python :: 3.10
Classifier: Programming Language :: Python :: 3.11
Requires-Dist: importlib (>=1.0.4,<2.0.0)
Requires-Dist: pyyaml (>=6.0.1,<7.0.0)
Requires-Dist: rdflib (>=7.0.0,<8.0.0)
Requires-Dist: validators (>=0.22.0,<0.23.0)
Project-URL: Documentation, https://w3id.org/ontouml/json2graph/docs
Project-URL: PyPi Project, https://pypi.org/project/ontouml-json2graph/
Project-URL: Repository, https://w3id.org/ontouml/json2graph
